{"nodes": [{"id": "c_users_itaym_documents_hw4_orchestration_graphify_project_4_src_hw4_gateway_overflow_queue_py", "label": "overflow_queue.py", "file_type": "code", "source_file": "src/hw4/gateway/overflow_queue.py", "source_location": "L1"}, {"id": "gateway_overflow_queue_overflowqueue", "label": "OverflowQueue", "file_type": "code", "source_file": "src/hw4/gateway/overflow_queue.py", "source_location": "L19"}, {"id": "gateway_overflow_queue_overflowqueue_init", "label": ".__init__()", "file_type": "code", "source_file": "src/hw4/gateway/overflow_queue.py", "source_location": "L22"}, {"id": "logger", "label": "Logger", "file_type": "code", "source_file": "src/hw4/gateway/overflow_queue.py", "source_location": "L22"}, {"id": "gateway_overflow_queue_overflowqueue_enqueue", "label": ".enqueue()", "file_type": "code", "source_file": "src/hw4/gateway/overflow_queue.py", "source_location": "L28"}, {"id": "any", "label": "Any", "file_type": "code", "source_file": "src/hw4/gateway/overflow_queue.py", "source_location": "L28"}, {"id": "gateway_overflow_queue_overflowqueue_peek", "label": ".peek()", "file_type": "code", "source_file": "src/hw4/gateway/overflow_queue.py", "source_location": "L40"}, {"id": "gateway_overflow_queue_overflowqueue_remove", "label": ".remove()", "file_type": "code", "source_file": "src/hw4/gateway/overflow_queue.py", "source_location": "L45"}, {"id": "gateway_overflow_queue_overflowqueue_is_full", "label": ".is_full()", "file_type": "code", "source_file": "src/hw4/gateway/overflow_queue.py", "source_location": "L54"}, {"id": "gateway_overflow_queue_overflowqueue_len", "label": ".__len__()", "file_type": "code", "source_file": "src/hw4/gateway/overflow_queue.py", "source_location": "L58"}, {"id": "gateway_overflow_queue_rationale_1", "label": "Bounded FIFO overflow queue for the API gatekeeper (\u00a75.3).  When the rate limite", "file_type": "rationale", "source_file": "src/hw4/gateway/overflow_queue.py", "source_location": "L1"}, {"id": "gateway_overflow_queue_rationale_20", "label": "Thread-safe FIFO queue with a hard depth cap and backpressure logging.", "file_type": "rationale", "source_file": "src/hw4/gateway/overflow_queue.py", "source_location": "L20"}, {"id": "gateway_overflow_queue_rationale_29", "label": "Append ``item`` in FIFO order; return ``False`` (alert) when full.", "file_type": "rationale", "source_file": "src/hw4/gateway/overflow_queue.py", "source_location": "L29"}, {"id": "gateway_overflow_queue_rationale_41", "label": "Return the head item without removing it (``None`` if empty).", "file_type": "rationale", "source_file": "src/hw4/gateway/overflow_queue.py", "source_location": "L41"}, {"id": "gateway_overflow_queue_rationale_46", "label": "Remove the first occurrence of ``item`` if present.", "file_type": "rationale", "source_file": "src/hw4/gateway/overflow_queue.py", "source_location": "L46"}], "edges": [{"source": "c_users_itaym_documents_hw4_orchestration_graphify_project_4_src_hw4_gateway_overflow_queue_py", "target": "logging", "relation": "imports", "context": "import", "confidence": "EXTRACTED", "source_file": "src/hw4/gateway/overflow_queue.py", "source_location": "L11", "weight": 1.0}, {"source": "c_users_itaym_documents_hw4_orchestration_graphify_project_4_src_hw4_gateway_overflow_queue_py", "target": "threading", "relation": "imports", "context": "import", "confidence": "EXTRACTED", "source_file": "src/hw4/gateway/overflow_queue.py", "source_location": "L12", "weight": 1.0}, {"source": "c_users_itaym_documents_hw4_orchestration_graphify_project_4_src_hw4_gateway_overflow_queue_py", "target": "collections", "relation": "imports_from", "context": "import", "confidence": "EXTRACTED", "source_file": "src/hw4/gateway/overflow_queue.py", "source_location": "L13", "weight": 1.0}, {"source": "c_users_itaym_documents_hw4_orchestration_graphify_project_4_src_hw4_gateway_overflow_queue_py", "target": "typing", "relation": "imports_from", "context": "import", "confidence": "EXTRACTED", "source_file": "src/hw4/gateway/overflow_queue.py", "source_location": "L14", "weight": 1.0}, {"source": "c_users_itaym_documents_hw4_orchestration_graphify_project_4_src_hw4_gateway_overflow_queue_py", "target": "hw4_constants", "relation": "imports_from", "context": "import", "confidence": "EXTRACTED", "source_file": "src/hw4/gateway/overflow_queue.py", "source_location": "L16", "weight": 1.0}, {"source": "c_users_itaym_documents_hw4_orchestration_graphify_project_4_src_hw4_gateway_overflow_queue_py", "target": "gateway_overflow_queue_overflowqueue", "relation": "contains", "confidence": "EXTRACTED", "source_file": "src/hw4/gateway/overflow_queue.py", "source_location": "L19", "weight": 1.0}, {"source": "gateway_overflow_queue_overflowqueue", "target": "gateway_overflow_queue_overflowqueue_init", "relation": "method", "confidence": "EXTRACTED", "source_file": "src/hw4/gateway/overflow_queue.py", "source_location": "L22", "weight": 1.0}, {"source": "gateway_overflow_queue_overflowqueue_init", "target": "logger", "relation": "references", "context": "parameter_type", "confidence": "EXTRACTED", "source_file": "src/hw4/gateway/overflow_queue.py", "source_location": "L22", "weight": 1.0}, {"source": "gateway_overflow_queue_overflowqueue", "target": "gateway_overflow_queue_overflowqueue_enqueue", "relation": "method", "confidence": "EXTRACTED", "source_file": "src/hw4/gateway/overflow_queue.py", "source_location": "L28", "weight": 1.0}, {"source": "gateway_overflow_queue_overflowqueue_enqueue", "target": "any", "relation": "references", "context": "parameter_type", "confidence": "EXTRACTED", "source_file": "src/hw4/gateway/overflow_queue.py", "source_location": "L28", "weight": 1.0}, {"source": "gateway_overflow_queue_overflowqueue", "target": "gateway_overflow_queue_overflowqueue_peek", "relation": "method", "confidence": "EXTRACTED", "source_file": "src/hw4/gateway/overflow_queue.py", "source_location": "L40", "weight": 1.0}, {"source": "gateway_overflow_queue_overflowqueue_peek", "target": "any", "relation": "references", "context": "return_type", "confidence": "EXTRACTED", "source_file": "src/hw4/gateway/overflow_queue.py", "source_location": "L40", "weight": 1.0}, {"source": "gateway_overflow_queue_overflowqueue", "target": "gateway_overflow_queue_overflowqueue_remove", "relation": "method", "confidence": "EXTRACTED", "source_file": "src/hw4/gateway/overflow_queue.py", "source_location": "L45", "weight": 1.0}, {"source": "gateway_overflow_queue_overflowqueue_remove", "target": "any", "relation": "references", "context": "parameter_type", "confidence": "EXTRACTED", "source_file": "src/hw4/gateway/overflow_queue.py", "source_location": "L45", "weight": 1.0}, {"source": "gateway_overflow_queue_overflowqueue", "target": "gateway_overflow_queue_overflowqueue_is_full", "relation": "method", "confidence": "EXTRACTED", "source_file": "src/hw4/gateway/overflow_queue.py", "source_location": "L54", "weight": 1.0}, {"source": "gateway_overflow_queue_overflowqueue", "target": "gateway_overflow_queue_overflowqueue_len", "relation": "method", "confidence": "EXTRACTED", "source_file": "src/hw4/gateway/overflow_queue.py", "source_location": "L58", "weight": 1.0}, {"source": "gateway_overflow_queue_rationale_1", "target": "c_users_itaym_documents_hw4_orchestration_graphify_project_4_src_hw4_gateway_overflow_queue_py", "relation": "rationale_for", "confidence": "EXTRACTED", "source_file": "src/hw4/gateway/overflow_queue.py", "source_location": "L1", "weight": 1.0}, {"source": "gateway_overflow_queue_rationale_20", "target": "gateway_overflow_queue_overflowqueue", "relation": "rationale_for", "confidence": "EXTRACTED", "source_file": "src/hw4/gateway/overflow_queue.py", "source_location": "L20", "weight": 1.0}, {"source": "gateway_overflow_queue_rationale_29", "target": "gateway_overflow_queue_overflowqueue_enqueue", "relation": "rationale_for", "confidence": "EXTRACTED", "source_file": "src/hw4/gateway/overflow_queue.py", "source_location": "L29", "weight": 1.0}, {"source": "gateway_overflow_queue_rationale_41", "target": "gateway_overflow_queue_overflowqueue_peek", "relation": "rationale_for", "confidence": "EXTRACTED", "source_file": "src/hw4/gateway/overflow_queue.py", "source_location": "L41", "weight": 1.0}, {"source": "gateway_overflow_queue_rationale_46", "target": "gateway_overflow_queue_overflowqueue_remove", "relation": "rationale_for", "confidence": "EXTRACTED", "source_file": "src/hw4/gateway/overflow_queue.py", "source_location": "L46", "weight": 1.0}], "raw_calls": [{"caller_nid": "gateway_overflow_queue_overflowqueue_init", "callee": "deque", "is_member_call": false, "source_file": "C:\\Users\\itaym\\Documents\\hw4-orchestration-graphify\\Project-4-\\src\\hw4\\gateway\\overflow_queue.py", "source_location": "L24"}, {"caller_nid": "gateway_overflow_queue_overflowqueue_init", "callee": "Lock", "is_member_call": true, "source_file": "C:\\Users\\itaym\\Documents\\hw4-orchestration-graphify\\Project-4-\\src\\hw4\\gateway\\overflow_queue.py", "source_location": "L25"}, {"caller_nid": "gateway_overflow_queue_overflowqueue_init", "callee": "getLogger", "is_member_call": true, "source_file": "C:\\Users\\itaym\\Documents\\hw4-orchestration-graphify\\Project-4-\\src\\hw4\\gateway\\overflow_queue.py", "source_location": "L26"}, {"caller_nid": "gateway_overflow_queue_overflowqueue_enqueue", "callee": "warning", "is_member_call": true, "source_file": "C:\\Users\\itaym\\Documents\\hw4-orchestration-graphify\\Project-4-\\src\\hw4\\gateway\\overflow_queue.py", "source_location": "L32"}, {"caller_nid": "gateway_overflow_queue_overflowqueue_enqueue", "callee": "append", "is_member_call": true, "source_file": "C:\\Users\\itaym\\Documents\\hw4-orchestration-graphify\\Project-4-\\src\\hw4\\gateway\\overflow_queue.py", "source_location": "L37"}]}